radio/__init__.py
radio/cli.py
radio/data/radios.json
radio-0.1.3.dist-info/entry_points.txt
radio-0.1.3.dist-info/LICENSE.txt
radio-0.1.3.dist-info/WHEEL
radio-0.1.3.dist-info/METADATA
radio-0.1.3.dist-info/RECORD
