Metadata-Version: 2.1
Name: radio
Version: 0.1.3
Summary: Just listen to the radio
Home-page: https://github.com/quijot/radio-package
License: WTFPL
Author: Santiago Pestarini
Author-email: santiagonob@gmail.com
Requires-Python: >=3.6
Classifier: License :: Other/Proprietary License
Classifier: Programming Language :: Python :: 3
Classifier: Programming Language :: Python :: 3.6
Classifier: Programming Language :: Python :: 3.7
Classifier: Programming Language :: Python :: 3.8
Requires-Dist: click (>=7,<8)
